SeoJiaochengV10/README.md
SeoJiaochengV10/__init__.py
SeoJiaochengV10/__main__.py
SeoJiaochengV10/file.epub
SeoJiaochengV10/index.html
SeoJiaochengV10/css/__init__.py
SeoJiaochengV10/css/annotations.css
SeoJiaochengV10/css/main.css
SeoJiaochengV10/css/normalize.css
SeoJiaochengV10/css/popup.css
SeoJiaochengV10/font/__init__.py
SeoJiaochengV10/font/fontello.eot
SeoJiaochengV10/font/fontello.svg
SeoJiaochengV10/font/fontello.ttf
SeoJiaochengV10/font/fontello.woff
SeoJiaochengV10/img/__init__.py
SeoJiaochengV10/img/annotator-glyph-sprite.png
SeoJiaochengV10/img/annotator-icon-sprite.png
SeoJiaochengV10/img/apple-touch-icon.png
SeoJiaochengV10/img/cancelfullscreen.png
SeoJiaochengV10/img/close.png
SeoJiaochengV10/img/fullscreen.png
SeoJiaochengV10/img/loader.gif
SeoJiaochengV10/img/menu-icon.png
SeoJiaochengV10/img/save.png
SeoJiaochengV10/img/saved.png
SeoJiaochengV10/img/settings-s.png
SeoJiaochengV10/img/settings.png
SeoJiaochengV10/img/star.png
SeoJiaochengV10/js/__init__.py
SeoJiaochengV10/js/epub.js
SeoJiaochengV10/js/epub.min.js
SeoJiaochengV10/js/epub.min.map
SeoJiaochengV10/js/hooks.min.js
SeoJiaochengV10/js/hooks.min.map
SeoJiaochengV10/js/reader.js
SeoJiaochengV10/js/reader.js.map
SeoJiaochengV10/js/reader.min.js
SeoJiaochengV10/js/reader.min.map
SeoJiaochengV10/js/hooks/__init__.py
SeoJiaochengV10/js/hooks/extensions/__init__.py
SeoJiaochengV10/js/hooks/extensions/highlight.js
SeoJiaochengV10/js/libs/__init__.py
SeoJiaochengV10/js/libs/jquery.min.js
SeoJiaochengV10/js/libs/localforage.min.js
SeoJiaochengV10/js/libs/screenfull.js
SeoJiaochengV10/js/libs/screenfull.min.js
SeoJiaochengV10/js/libs/zip.min.js
SeoJiaochengV10/js/plugins/__init__.py
SeoJiaochengV10/js/plugins/hypothesis.js
SeoJiaochengV10/js/plugins/search.js
seo_jiaocheng_v1_0-2024.3.2.0.dist-info/METADATA
seo_jiaocheng_v1_0-2024.3.2.0.dist-info/WHEEL
seo_jiaocheng_v1_0-2024.3.2.0.dist-info/entry_points.txt
seo_jiaocheng_v1_0-2024.3.2.0.dist-info/top_level.txt
seo_jiaocheng_v1_0-2024.3.2.0.dist-info/RECORD
